nonebot_plugin_impact/__init__.py
nonebot_plugin_impact/data_sheet.py
nonebot_plugin_impact/draw_img.py
nonebot_plugin_impact/handle.py
nonebot_plugin_impact/txt2img.py
nonebot_plugin_impact/utils.py
nonebot_plugin_impact/fonts/SIMYOU.TTF
nonebot_plugin_impact-0.12.114514.dist-info/LICENSE
nonebot_plugin_impact-0.12.114514.dist-info/METADATA
nonebot_plugin_impact-0.12.114514.dist-info/WHEEL
nonebot_plugin_impact-0.12.114514.dist-info/top_level.txt
nonebot_plugin_impact-0.12.114514.dist-info/RECORD
