Metadata-Version: 2.1
Name: nonebot-plugin-impact
Version: 0.12.114514
Summary: 让群友们眼前一黑的nonebot2淫趴插件
Home-page: https://github.com/Special-Week/nonebot_plugin_impact
Author: Special-Week
Author-email: HuaMing27499@gmail.com
Requires-Python: >=3.8.0
License-File: LICENSE
Requires-Dist: pillow
Requires-Dist: nonebot2
Requires-Dist: nonebot-adapter-onebot
Requires-Dist: sqlalchemy
Requires-Dist: nonebot-plugin-apscheduler
Requires-Dist: httpx
